etc/systemd/system/zymkey-filesystem@.service
zku-1.0.33.data/data/LICENSE.txt
zku-1.0.33.data/data/config/logconfig.yml
zku-1.0.33.data/data/config/settings.yml
zymkey/__init__.py
zymkey/entrypoints.py
zymkey/exceptions.py
zymkey/filesystem.py
zymkey/settings.py
zymkey/utils.py
zymkey/vault.py
zymkey/zka.py
zymkey/commands/__init__.py
zymkey/commands/filesystem_create.py
zymkey/commands/filesystem_mount.py
zymkey/commands/filesystem_unmount.py
zymkey/commands/lock.py
zymkey/commands/random.py
zymkey/commands/unlock.py
zku-1.0.33.dist-info/LICENSE.txt
zku-1.0.33.dist-info/METADATA
zku-1.0.33.dist-info/WHEEL
zku-1.0.33.dist-info/entry_points.txt
zku-1.0.33.dist-info/top_level.txt
zku-1.0.33.dist-info/RECORD
