Metadata-Version: 2.1
Name: zku
Version: 1.0.33
Summary: Zymkey utilities
Home-page: https://zymbit.com/
Author: Zymbit, Inc.
Author-email: code@zymbit.com
License: LICENSE.txt
Platform: UNKNOWN
Requires-Dist: cmdline (>=0.1.8)
Requires-Dist: sh (>=1.11)
